MANIFEST.in
README.rst
setup.cfg
setup.py
docs/__init__.py
docs/conf.py
megatroniki.egg-info/PKG-INFO
megatroniki.egg-info/SOURCES.txt
megatroniki.egg-info/dependency_links.txt
megatroniki.egg-info/entry_points.txt
megatroniki.egg-info/requires.txt
megatroniki.egg-info/top_level.txt
tests/__init__.py
tests/test_core.py
tests/test_user.py
tests/test_web.py
wiki/__init__.py
wiki/cli.py
wiki/core.py
wiki/web/__init__.py
wiki/web/forms.py
wiki/web/routes.py
wiki/web/user.py
wiki/web/static/bootstrap.css
wiki/web/static/bootstrap.min.js
wiki/web/static/jquery.min.js
wiki/web/static/pygments.css
wiki/web/static/responsive.css
wiki/web/templates/404.html
wiki/web/templates/admin.html
wiki/web/templates/base.html
wiki/web/templates/create.html
wiki/web/templates/ebook.html
wiki/web/templates/editor.html
wiki/web/templates/helpers.html
wiki/web/templates/home.html
wiki/web/templates/index.html
wiki/web/templates/login.html
wiki/web/templates/move.html
wiki/web/templates/page.html
wiki/web/templates/search.html
wiki/web/templates/settings.html
wiki/web/templates/tag.html
wiki/web/templates/tags.html