Metadata-Version: 1.1
Name: megatroniki
Version: 1.0.0
Summary: simple python markdown wiki with web ui and commandline interface
Home-page: https://github.com/konzy/CSC440-Wiki-Project
Author: Ethan Gallagher, Brian Konzman, Katie Schwegman
Author-email: megatroniki2017@gmail.com
License: UNKNOWN
Platform: UNKNOWN
Classifier: Development Status :: 5 - Production/Stable
Classifier: Intended Audience :: Developers
Classifier: Topic :: Software Development
Classifier: Programming Language :: Python :: 2
Classifier: Programming Language :: Python :: 2.6
Classifier: Programming Language :: Python :: 2.7
